Mixstable/__init__.py
Mixstable/bayesian.py
Mixstable/ecf.py
Mixstable/ecf_estimators.py
Mixstable/em.py
Mixstable/em_methode.py
Mixstable/em_methode_with_gibbs.py
Mixstable/evaluation.py
Mixstable/generate_sample.py
Mixstable/gibbs.py
Mixstable/mcculloch.py
Mixstable/metrics.py
Mixstable/mle.py
Mixstable/quantiles.py
Mixstable/r_interface.py
Mixstable/rt_estimation.py
Mixstable/simulations.py
Mixstable/stable_mixture_estimators.py
Mixstable/testing_data.py
Mixstable/utils.py
Mixstable/visualization.py
interface/__init__.py
interface/app.py
interface/app_v2.py
interface/em_robust.py
interface/preprocess.py
interface/rpy2_init.py
mixstable-0.1.8.dist-info/METADATA
mixstable-0.1.8.dist-info/WHEEL
mixstable-0.1.8.dist-info/top_level.txt
mixstable-0.1.8.dist-info/RECORD
