Metadata-Version: 2.4
Name: Mixstable
Version: 0.1.8
Summary: Parameter estimation tools for one-dimensional stable distributions and their mixtures.
Home-page: https://github.com/AdamNajib/MixStable
Author: Solym Manou-Abi, Adam Najib, Yousri Slaoui
Classifier: Programming Language :: Python :: 3
Classifier: Operating System :: OS Independent
Requires-Python: >=3.8
Requires-Dist: numpy
Requires-Dist: scipy
Requires-Dist: pandas
Requires-Dist: matplotlib
Requires-Dist: scikit-learn
Requires-Dist: streamlit
Requires-Dist: statsmodels
Requires-Dist: rpy2
Dynamic: author
Dynamic: classifier
Dynamic: description
Dynamic: description-content-type
Dynamic: home-page
Dynamic: requires-dist
Dynamic: requires-python
Dynamic: summary
